{
  "1011": {
    "name": "Anby",
    "version": 1,
    "quality": 4,
    "element": "electric",
    "type": "stun",
    "baseStats": {
      "baseHp": 7501,
      "baseAtk": 584,
      "baseDef": 613,
      "baseImpact": 118,
      "baseAnomalyMastery": 94,
      "baseAnomalyProficiency": 93
    },
    "ascensionStats": {
      "baseImpact": 18,
      "baseAtk": 75
    },
    "effects": []
  },
  "1021": {
    "name": "Nekomata",
    "version": 1,
    "quality": 5,
    "element": "physical",
    "type": "attack",
    "baseStats": {
      "baseHp": 7560,
      "baseAtk": 836,
      "baseDef": 588,
      "baseImpact": 92,
      "baseAnomalyMastery": 97,
      "baseAnomalyProficiency": 96
    },
    "ascensionStats": {
      "critRate%": 0.144,
      "baseAtk": 75
    },
    "effects": []
  },
  "1031": {
    "name": "Nicole",
    "version": 1,
    "quality": 4,
    "element": "ether",
    "type": "support",
    "baseStats": {
      "baseHp": 8146,
      "baseAtk": 574,
      "baseDef": 623,
      "baseImpact": 88,
      "baseAnomalyMastery": 90,
      "baseAnomalyProficiency": 93
    },
    "ascensionStats": {
      "baseEnergyRegen": 36,
      "baseAtk": 75
    },
    "effects": []
  },
  "1041": {
    "name": "Soldier 11",
    "version": 1,
    "quality": 5,
    "element": "fire",
    "type": "attack",
    "baseStats": {
      "baseHp": 7674,
      "baseAtk": 814,
      "baseDef": 613,
      "baseImpact": 93,
      "baseAnomalyMastery": 94,
      "baseAnomalyProficiency": 93
    },
    "ascensionStats": {
      "critRate%": 0.144,
      "baseAtk": 75
    },
    "effects": []
  },
  "1061": {
    "name": "Corin",
    "version": 1,
    "quality": 4,
    "element": "physical",
    "type": "attack",
    "baseStats": {
      "baseHp": 6977,
      "baseAtk": 732,
      "baseDef": 605,
      "baseImpact": 93,
      "baseAnomalyMastery": 93,
      "baseAnomalyProficiency": 96
    },
    "ascensionStats": {
      "critDmg%": 0.288,
      "baseAtk": 75
    },
    "effects": []
  },
  "1081": {
    "name": "Billy",
    "version": 1,
    "quality": 4,
    "element": "physical",
    "type": "attack",
    "baseStats": {
      "baseHp": 6907,
      "baseAtk": 712,
      "baseDef": 607,
      "baseImpact": 91,
      "baseAnomalyMastery": 92,
      "baseAnomalyProficiency": 91
    },
    "ascensionStats": {
      "critRate%": 0.144,
      "baseAtk": 75
    },
    "effects": []
  },
  "1101": {
    "name": "Koleda",
    "version": 1,
    "quality": 5,
    "element": "fire",
    "type": "stun",
    "baseStats": {
      "baseHp": 8127,
      "baseAtk": 661,
      "baseDef": 595,
      "baseImpact": 116,
      "baseAnomalyMastery": 97,
      "baseAnomalyProficiency": 96
    },
    "ascensionStats": {
      "baseImpact": 18,
      "baseAtk": 75
    },
    "effects": []
  },
  "1111": {
    "name": "Anton",
    "version": 1,
    "quality": 4,
    "element": "electric",
    "type": "attack",
    "baseStats": {
      "baseHp": 7219,
      "baseAtk": 717,
      "baseDef": 623,
      "baseImpact": 95,
      "baseAnomalyMastery": 86,
      "baseAnomalyProficiency": 90
    },
    "ascensionStats": {
      "critRate%": 0.144,
      "baseAtk": 75
    },
    "effects": []
  },
  "1121": {
    "name": "Ben",
    "version": 1,
    "quality": 4,
    "element": "fire",
    "type": "defense",
    "baseStats": {
      "baseHp": 8578,
      "baseAtk": 578,
      "baseDef": 724,
      "baseImpact": 95,
      "baseAnomalyMastery": 86,
      "baseAnomalyProficiency": 90
    },
    "ascensionStats": {
      "baseEnergyRegen": 36,
      "baseAtk": 75
    },
    "effects": []
  },
  "1131": {
    "name": "Soukaku",
    "version": 1,
    "quality": 4,
    "element": "ice",
    "type": "support",
    "baseStats": {
      "baseHp": 8026,
      "baseAtk": 591,
      "baseDef": 598,
      "baseImpact": 86,
      "baseAnomalyMastery": 93,
      "baseAnomalyProficiency": 96
    },
    "ascensionStats": {
      "baseEnergyRegen": 36,
      "baseAtk": 75
    },
    "effects": []
  },
  "1141": {
    "name": "Lycaon",
    "version": 1,
    "quality": 5,
    "element": "ice",
    "type": "stun",
    "baseStats": {
      "baseHp": 8416,
      "baseAtk": 654,
      "baseDef": 607,
      "baseImpact": 119,
      "baseAnomalyMastery": 91,
      "baseAnomalyProficiency": 90
    },
    "ascensionStats": {
      "baseImpact": 18,
      "baseAtk": 75
    },
    "effects": []
  },
  "1151": {
    "name": "Lucy",
    "version": 1,
    "quality": 4,
    "element": "fire",
    "type": "support",
    "baseStats": {
      "baseHp": 8026,
      "baseAtk": 584,
      "baseDef": 613,
      "baseImpact": 86,
      "baseAnomalyMastery": 94,
      "baseAnomalyProficiency": 93
    },
    "ascensionStats": {
      "baseEnergyRegen": 36,
      "baseAtk": 75
    },
    "effects": []
  },
  "1181": {
    "name": "Grace",
    "version": 1,
    "quality": 5,
    "element": "electric",
    "type": "anomaly",
    "baseStats": {
      "baseHp": 7483,
      "baseAtk": 751,
      "baseDef": 601,
      "baseImpact": 83,
      "baseAnomalyMastery": 115,
      "baseAnomalyProficiency": 116
    },
    "ascensionStats": {
      "baseAnomalyMastery": 36,
      "baseAtk": 75
    },
    "effects": []
  },
  "1191": {
    "name": "Ellen",
    "version": 1,
    "quality": 5,
    "element": "ice",
    "type": "attack",
    "baseStats": {
      "baseHp": 7674,
      "baseAtk": 863,
      "baseDef": 607,
      "baseImpact": 93,
      "baseAnomalyMastery": 94,
      "baseAnomalyProficiency": 93
    },
    "ascensionStats": {
      "critRate%": 0.144,
      "baseAtk": 75
    },
    "effects": []
  },
  "1211": {
    "name": "Rina",
    "version": 1,
    "quality": 5,
    "element": "electric",
    "type": "support",
    "baseStats": {
      "baseHp": 8609,
      "baseAtk": 642,
      "baseDef": 601,
      "baseImpact": 83,
      "baseAnomalyMastery": 93,
      "baseAnomalyProficiency": 92
    },
    "ascensionStats": {
      "penRatio%": 0.144,
      "baseAtk": 75
    },
    "effects": []
  },
  "1241": {
    "name": "Zhu Yuan",
    "version": 1,
    "quality": 5,
    "element": "ether",
    "type": "attack",
    "baseStats": {
      "baseHp": 7483,
      "baseAtk": 844,
      "baseDef": 601,
      "baseImpact": 90,
      "baseAnomalyMastery": 93,
      "baseAnomalyProficiency": 92
    },
    "ascensionStats": {
      "critDmg%": 0.288,
      "baseAtk": 75
    },
    "effects": []
  },
  "1281": {
    "name": "Piper",
    "version": 1,
    "quality": 4,
    "element": "physical",
    "type": "anomaly",
    "baseStats": {
      "baseHp": 6977,
      "baseAtk": 683,
      "baseDef": 613,
      "baseImpact": 86,
      "baseAnomalyMastery": 116,
      "baseAnomalyProficiency": 118
    },
    "ascensionStats": {
      "baseEnergyRegen": 36,
      "baseAtk": 75
    },
    "effects": []
  },
  "1251": {
    "name": "Qingyi",
    "version": 1.1,
    "quality": 5,
    "element": "electric",
    "type": "stun",
    "baseStats": {
      "baseHp": 8251,
      "baseAtk": 683,
      "baseDef": 613,
      "baseImpact": 118,
      "baseAnomalyMastery": 94,
      "baseAnomalyProficiency": 93
    },
    "ascensionStats": {
      "baseImpact": 18,
      "baseAtk": 75
    },
    "effects": []
  },
  "1261": {
    "name": "Jane",
    "version": 1.1,
    "quality": 5,
    "element": "physical",
    "type": "anomaly",
    "baseStats": {
      "baseHp": 7789,
      "baseAtk": 806,
      "baseDef": 607,
      "baseImpact": 86,
      "baseAnomalyMastery": 112,
      "baseAnomalyProficiency": 114
    },
    "ascensionStats": {
      "baseAnomalyMastery": 36,
      "baseAtk": 75
    },
    "effects": []
  },
  "1271": {
    "name": "Seth",
    "version": 1.1,
    "quality": 4,
    "element": "electric",
    "type": "defense",
    "baseStats": {
      "baseHp": 8701,
      "baseAtk": 568,
      "baseDef": 746,
      "baseImpact": 94,
      "baseAnomalyMastery": 86,
      "baseAnomalyProficiency": 90
    },
    "ascensionStats": {
      "baseEnergyRegen": 36,
      "baseAtk": 75
    },
    "effects": []
  },
  "1071": {
    "name": "Caesar",
    "version": 1.2,
    "quality": 5,
    "element": "physical",
    "type": "defense",
    "baseStats": {
      "baseHp": 9526,
      "baseAtk": 637,
      "baseDef": 754,
      "baseImpact": 105,
      "baseAnomalyMastery": 87,
      "baseAnomalyProficiency": 90
    },
    "ascensionStats": {
      "baseImpact": 18,
      "baseAtk": 75
    },
    "effects": []
  },
  "1171": {
    "name": "Burnice",
    "version": 1.2,
    "quality": 5,
    "element": "fire",
    "type": "anomaly",
    "baseStats": {
      "baseHp": 7368,
      "baseAtk": 788,
      "baseDef": 601,
      "baseImpact": 83,
      "baseAnomalyMastery": 118,
      "baseAnomalyProficiency": 120
    },
    "ascensionStats": {
      "baseEnergyRegen": 36,
      "baseAtk": 75
    },
    "effects": []
  },
  "1161": {
    "name": "Lighter",
    "version": 1.3,
    "quality": 5,
    "element": "fire",
    "type": "stun",
    "baseStats": {
      "baseHp": 8253,
      "baseAtk": 723,
      "baseDef": 613,
      "baseImpact": 119,
      "baseAnomalyMastery": 91,
      "baseAnomalyProficiency": 90
    },
    "ascensionStats": {
      "baseImpact": 18,
      "baseAtk": 75
    },
    "effects": []
  },
  "1221": {
    "name": "Yanagi",
    "version": 1.3,
    "quality": 5,
    "element": "electric",
    "type": "anomaly",
    "baseStats": {
      "baseHp": 7789,
      "baseAtk": 798,
      "baseDef": 613,
      "baseImpact": 86,
      "baseAnomalyMastery": 112,
      "baseAnomalyProficiency": 114
    },
    "ascensionStats": {
      "baseAnomalyMastery": 36,
      "baseAtk": 75
    },
    "effects": []
  },
  "1091": {
    "name": "Miyabi",
    "version": 1.4,
    "quality": 5,
    "element": "ice",
    "type": "anomaly",
    "baseStats": {
      "baseHp": 7674,
      "baseAtk": 806,
      "baseDef": 607,
      "baseImpact": 86,
      "baseAnomalyMastery": 116,
      "baseAnomalyProficiency": 148
    },
    "ascensionStats": {
      "baseAnomalyProficiency": 90,
      "baseAtk": 75
    },
    "effects": []
  },
  "1201": {
    "name": "Harumasa",
    "version": 1.4,
    "quality": 5,
    "element": "electric",
    "type": "attack",
    "baseStats": {
      "baseHp": 7406,
      "baseAtk": 841,
      "baseDef": 601,
      "baseImpact": 90,
      "baseAnomalyMastery": 80,
      "baseAnomalyProficiency": 95
    },
    "ascensionStats": {
      "critRate%": 0.144,
      "baseAtk": 75
    },
    "effects": []
  },
  "1311": {
    "name": "Astra Yao",
    "version": 1.5,
    "quality": 5,
    "element": "ether",
    "type": "support",
    "baseStats": {
      "baseHp": 8609,
      "baseAtk": 641,
      "baseDef": 601,
      "baseImpact": 83,
      "baseAnomalyMastery": 93,
      "baseAnomalyProficiency": 92
    },
    "ascensionStats": {
      "baseEnergyRegen": 36,
      "baseAtk": 75
    },
    "effects": []
  },
  "1321": {
    "name": "Evelyn",
    "version": 1.5,
    "quality": 5,
    "element": "fire",
    "type": "attack",
    "baseStats": {
      "baseHp": 7789,
      "baseAtk": 855,
      "baseDef": 613,
      "baseImpact": 93,
      "baseAnomalyMastery": 92,
      "baseAnomalyProficiency": 90
    },
    "ascensionStats": {
      "critRate%": 0.144,
      "baseAtk": 75
    },
    "effects": []
  },
  "1351": {
    "name": "Pulchra",
    "version": 1.6,
    "quality": 4,
    "element": "physical",
    "type": "stun",
    "baseStats": {
      "baseHp": 7613,
      "baseAtk": 591,
      "baseDef": 607,
      "baseImpact": 118,
      "baseAnomalyMastery": 92,
      "baseAnomalyProficiency": 90
    },
    "ascensionStats": {
      "baseImpact": 18,
      "baseAtk": 75
    },
    "effects": []
  },
  "1361": {
    "name": "Trigger",
    "version": 1.6,
    "quality": 5,
    "element": "electric",
    "type": "stun",
    "baseStats": {
      "baseHp": 7923,
      "baseAtk": 676,
      "baseDef": 601,
      "baseImpact": 113,
      "baseAnomalyMastery": 96,
      "baseAnomalyProficiency": 95
    },
    "ascensionStats": {
      "baseImpact": 18,
      "baseAtk": 75
    },
    "effects": []
  },
  "1381": {
    "name": "Soldier 0 - Anby",
    "version": 1.6,
    "quality": 5,
    "element": "electric",
    "type": "attack",
    "baseStats": {
      "baseHp": 7674,
      "baseAtk": 855,
      "baseDef": 613,
      "baseImpact": 93,
      "baseAnomalyMastery": 94,
      "baseAnomalyProficiency": 93
    },
    "ascensionStats": {
      "critRate%": 0.144,
      "baseAtk": 75
    },
    "effects": []
  },
  "1291": {
    "name": "Hugo",
    "version": 1.7,
    "quality": 5,
    "element": "ice",
    "type": "attack",
    "baseStats": {
      "baseHp": 7941,
      "baseAtk": 844,
      "baseDef": 617,
      "baseImpact": 95,
      "baseAnomalyMastery": 86,
      "baseAnomalyProficiency": 90
    },
    "ascensionStats": {
      "critRate%": 0.144,
      "baseAtk": 75
    },
    "effects": []
  },
  "1331": {
    "name": "Vivian",
    "version": 1.7,
    "quality": 5,
    "element": "ether",
    "type": "anomaly",
    "baseStats": {
      "baseHp": 7674,
      "baseAtk": 806,
      "baseDef": 607,
      "baseImpact": 86,
      "baseAnomalyMastery": 108,
      "baseAnomalyProficiency": 118
    },
    "ascensionStats": {
      "baseAnomalyMastery": 36,
      "baseAtk": 75
    },
    "effects": []
  },
  "1371": {
    "name": "Yixuan",
    "version": 2,
    "quality": 5,
    "element": "ether",
    "type": "rupture",
    "baseStats": {
      "baseHp": 7954,
      "baseAtk": 873,
      "baseDef": 441,
      "baseImpact": 93,
      "baseAnomalyMastery": 92,
      "baseAnomalyProficiency": 90
    },
    "ascensionStats": {
      "critRate%": 0.144,
      "baseHp": 420
    },
    "effects": []
  },
  "1391": {
    "name": "Ju Fufu",
    "version": 2,
    "quality": 5,
    "element": "fire",
    "type": "stun",
    "baseStats": {
      "baseHp": 8251,
      "baseAtk": 691,
      "baseDef": 598,
      "baseImpact": 118,
      "baseAnomalyMastery": 93,
      "baseAnomalyProficiency": 96
    },
    "ascensionStats": {
      "critRate%": 0.144,
      "baseAtk": 75
    },
    "effects": []
  },
  "1421": {
    "name": "Pan Yinhu",
    "version": 2,
    "quality": 4,
    "element": "physical",
    "type": "defense",
    "baseStats": {
      "baseHp": 8454,
      "baseAtk": 587,
      "baseDef": 713,
      "baseImpact": 94,
      "baseAnomalyMastery": 91,
      "baseAnomalyProficiency": 90
    },
    "ascensionStats": {
      "baseEnergyRegen": 36,
      "baseAtk": 75
    },
    "effects": []
  },
  "1401": {
    "name": "Alice",
    "version": 2.1,
    "quality": 5,
    "element": "physical",
    "type": "anomaly",
    "baseStats": {
      "baseHp": 7674,
      "baseAtk": 806,
      "baseDef": 607,
      "baseImpact": 86,
      "baseAnomalyMastery": 106,
      "baseAnomalyProficiency": 118
    },
    "ascensionStats": {
      "baseAnomalyMastery": 36,
      "baseAtk": 75
    },
    "effects": []
  },
  "1411": {
    "name": "Yuzuha",
    "version": 2.1,
    "quality": 5,
    "element": "physical",
    "type": "support",
    "baseStats": {
      "baseHp": 8829,
      "baseAtk": 683,
      "baseDef": 613,
      "baseImpact": 86,
      "baseAnomalyMastery": 88,
      "baseAnomalyProficiency": 93
    },
    "ascensionStats": {
      "baseAnomalyMastery": 36,
      "baseAtk": 75
    },
    "effects": []
  },
  "1301": {
    "name": "Orphie & Magus",
    "version": 2.2,
    "quality": 5,
    "element": "fire",
    "type": "attack",
    "baseStats": {
      "baseHp": 7789,
      "baseAtk": 855,
      "baseDef": 613,
      "baseImpact": 93,
      "baseAnomalyMastery": 92,
      "baseAnomalyProficiency": 90
    },
    "ascensionStats": {
      "baseEnergyRegen": 36,
      "baseAtk": 75
    },
    "effects": []
  },
  "1461": {
    "name": "Seed",
    "version": 2.2,
    "quality": 5,
    "element": "electric",
    "type": "attack",
    "baseStats": {
      "baseHp": 7674,
      "baseAtk": 855,
      "baseDef": 613,
      "baseImpact": 93,
      "baseAnomalyMastery": 94,
      "baseAnomalyProficiency": 93
    },
    "ascensionStats": {
      "critDmg%": 0.288,
      "baseAtk": 75
    },
    "effects": []
  },
  "1051": {
    "name": "Yidhari",
    "version": 2.3,
    "quality": 5,
    "element": "ice",
    "type": "rupture",
    "baseStats": {
      "baseHp": 8497,
      "baseAtk": 785,
      "baseDef": 448,
      "baseImpact": 95,
      "baseAnomalyMastery": 87,
      "baseAnomalyProficiency": 90
    },
    "ascensionStats": {
      "critRate%": 0.144,
      "baseAtk": 75
    },
    "effects": []
  },
  "1441": {
    "name": "Manato",
    "version": 2.3,
    "quality": 4,
    "element": "fire",
    "type": "rupture",
    "baseStats": {
      "baseHp": 7725,
      "baseAtk": 680,
      "baseDef": 444,
      "baseImpact": 95,
      "baseAnomalyMastery": 87,
      "baseAnomalyProficiency": 90
    },
    "ascensionStats": {
      "hp%": 0.18,
      "baseAtk": 75
    },
    "effects": []
  },
  "1451": {
    "name": "Lucia",
    "version": 2.3,
    "quality": 5,
    "element": "ether",
    "type": "support",
    "baseStats": {
      "baseHp": 8477,
      "baseAtk": 683,
      "baseDef": 595,
      "baseImpact": 83,
      "baseAnomalyMastery": 96,
      "baseAnomalyProficiency": 95
    },
    "ascensionStats": {
      "baseEnergyRegen": 36,
      "baseAtk": 75
    },
    "effects": []
  },
  "1471": {
    "name": "Banyue",
    "version": 2.4,
    "quality": 5,
    "element": "fire",
    "type": "rupture",
    "baseStats": {
      "baseHp": 8497,
      "baseAtk": 785,
      "baseDef": 446,
      "baseImpact": 95,
      "baseAnomalyMastery": 90,
      "baseAnomalyProficiency": 89
    },
    "ascensionStats": {
      "critRate%": 0.144,
      "baseAtk": 75
    },
    "effects": []
  },
  "1481": {
    "name": "Dialyn",
    "version": 2.4,
    "quality": 5,
    "element": "physical",
    "type": "stun",
    "baseStats": {
      "baseHp": 8251,
      "baseAtk": 683,
      "baseDef": 613,
      "baseImpact": 110,
      "baseAnomalyMastery": 94,
      "baseAnomalyProficiency": 93
    },
    "ascensionStats": {
      "critRate%": 0.144,
      "baseAtk": 75
    },
    "effects": []
  },
  "1341": {
    "name": "Zhao",
    "version": 2.5,
    "quality": 5,
    "element": "ice",
    "type": "defense",
    "baseStats": {
      "baseHp": 9117,
      "baseAtk": 691,
      "baseDef": 702,
      "baseImpact": 93,
      "baseAnomalyMastery": 93,
      "baseAnomalyProficiency": 96
    },
    "ascensionStats": {
      "hp%": 0.18,
      "baseAtk": 75
    },
    "effects": []
  },
  "1431": {
    "name": "Ye Shunguang",
    "version": 2.5,
    "quality": 5,
    "element": "physical",
    "type": "attack",
    "baseStats": {
      "baseHp": 7674,
      "baseAtk": 863,
      "baseDef": 607,
      "baseImpact": 83,
      "baseAnomalyMastery": 94,
      "baseAnomalyProficiency": 93
    },
    "ascensionStats": {
      "critRate%": 0.144,
      "baseAtk": 75
    },
    "effects": []
  },
  "1491": {
    "name": "Sunna",
    "version": 2.6,
    "quality": 5,
    "element": "physical",
    "type": "support",
    "baseStats": {
      "baseHp": 8477,
      "baseAtk": 676,
      "baseDef": 601,
      "baseImpact": 98,
      "baseAnomalyMastery": 96,
      "baseAnomalyProficiency": 95
    },
    "ascensionStats": {
      "atk%": 0.21,
      "baseAtk": 75
    },
    "effects": []
  },
  "1501": {
    "name": "Aria",
    "version": 2.6,
    "quality": 5,
    "element": "ether",
    "type": "anomaly",
    "baseStats": {
      "baseHp": 7750,
      "baseAtk": 788,
      "baseDef": 620,
      "baseImpact": 87,
      "baseAnomalyMastery": 115,
      "baseAnomalyProficiency": 116
    },
    "ascensionStats": {
      "baseAnomalyMastery": 36,
      "baseAtk": 75
    },
    "effects": []
  },
  "1511": {
    "name": "Nangong Yu",
    "version": 2.7,
    "quality": 5,
    "element": "ether",
    "type": "stun",
    "baseStats": {
      "baseHp": 8374,
      "baseAtk": 672,
      "baseDef": 623,
      "baseImpact": 120,
      "baseAnomalyMastery": 90,
      "baseAnomalyProficiency": 93
    },
    "ascensionStats": {
      "baseAnomalyMastery": 36,
      "baseAtk": 75
    },
    "effects": []
  },
  "1521": {
    "name": "Cissia",
    "version": 2.7,
    "quality": 5,
    "element": "electric",
    "type": "attack",
    "baseStats": {
      "baseHp": 7674,
      "baseAtk": 863,
      "baseDef": 607,
      "baseImpact": 93,
      "baseAnomalyMastery": 94,
      "baseAnomalyProficiency": 93
    },
    "ascensionStats": {
      "baseEnergyRegen": 36,
      "baseAtk": 75
    },
    "effects": []
  },
  "1531": {
    "name": "Starlight - Billy",
    "version": 2.8,
    "quality": 5,
    "element": "physical",
    "type": "rupture",
    "baseStats": {
      "baseHp": 8497,
      "baseAtk": 785,
      "baseDef": 446,
      "baseImpact": 95,
      "baseAnomalyMastery": 90,
      "baseAnomalyProficiency": 89
    },
    "ascensionStats": {
      "critRate%": 0.144,
      "baseAtk": 75
    },
    "effects": []
  },
  "1541": {
    "name": "Promeia",
    "version": 2.8,
    "quality": 5,
    "element": "ice",
    "type": "anomaly",
    "baseStats": {
      "baseHp": 7789,
      "baseAtk": 798,
      "baseDef": 613,
      "baseImpact": 86,
      "baseAnomalyMastery": 112,
      "baseAnomalyProficiency": 114
    },
    "ascensionStats": {
      "baseAnomalyMastery": 36,
      "baseAtk": 75
    },
    "effects": []
  },
  "1551": {
    "name": "Pyrois",
    "version": 3,
    "quality": 5,
    "element": "ether",
    "type": "attack",
    "baseStats": {
      "baseHp": 7674,
      "baseAtk": 849,
      "baseDef": 613,
      "baseImpact": 94,
      "baseAnomalyMastery": 94,
      "baseAnomalyProficiency": 93
    },
    "ascensionStats": {
      "critRate%": 0.144,
      "baseAtk": 75
    },
    "effects": []
  },
  "1561": {
    "name": "Velina",
    "version": 3,
    "quality": 5,
    "element": "wind",
    "type": "anomaly",
    "baseStats": {
      "baseHp": 7789,
      "baseAtk": 798,
      "baseDef": 613,
      "baseImpact": 86,
      "baseAnomalyMastery": 112,
      "baseAnomalyProficiency": 111
    },
    "ascensionStats": {
      "baseAnomalyProficiency": 54,
      "baseAtk": 75
    },
    "effects": []
  },
  "1571": {
    "name": "Norma",
    "version": 3,
    "quality": 5,
    "element": "fire",
    "type": "stun",
    "baseStats": {
      "baseHp": 7800,
      "baseAtk": 687,
      "baseDef": 583,
      "baseImpact": 106,
      "baseAnomalyMastery": 99,
      "baseAnomalyProficiency": 98
    },
    "ascensionStats": {
      "critRate%": 0.144,
      "baseAtk": 75
    },
    "effects": []
  }
}